awsm_rank/__init__.py
awsm_rank/awsm_rank.py
awsm_rank-0.1.1.dist-info/LICENSE
awsm_rank-0.1.1.dist-info/METADATA
awsm_rank-0.1.1.dist-info/WHEEL
awsm_rank-0.1.1.dist-info/entry_points.txt
awsm_rank-0.1.1.dist-info/top_level.txt
awsm_rank-0.1.1.dist-info/RECORD
