Metadata-Version: 2.1
Name: awsm-rank
Version: 0.1.1
Summary: Ranks github repo entries on github pages from the 'Awesome' series
Home-page: https://github.com/psacawa/awsm-rank
Author: Paweł Sacawa
License: UNKNOWN
Platform: UNKNOWN
License-File: LICENSE
Requires-Dist: aiohttp
Requires-Dist: bs4
Requires-Dist: tabulate
Requires-Dist: requests
